{
  "main": {
    "id": "7b793816d23c7d05",
    "type": "split",
    "children": [
      {
        "id": "2924ef31d62a9cac",
        "type": "tabs",
        "children": [
          {
            "id": "17f50fb0cbf36efc",
            "type": "leaf",
            "pinned": true,
            "state": {
              "type": "graph",
              "state": {},
              "pinned": true,
              "icon": "lucide-git-fork",
              "title": "关系图谱"
            }
          },
          {
            "id": "9c62602861d7e747",
            "type": "leaf",
            "state": {
              "type": "markdown",
              "state": {
                "file": "【文章目录】/【1 - 哲学类】/190 - 伦理学/198 - 职业伦理/选择与规划/程序员前景.md",
                "mode": "source",
                "source": false
              },
              "icon": "lucide-file",
              "title": "程序员前景"
            }
          },
          {
            "id": "b1b9873c78a73de2",
            "type": "leaf",
            "state": {
              "type": "markdown",
              "state": {
                "file": "【文章目录】/【1 - 哲学类】/170 - 心理学/173 - 一般心理/情绪/失望.md",
                "mode": "source",
                "source": false
              },
              "icon": "lucide-file",
              "title": "失望"
            }
          },
          {
            "id": "06b546f6b6740145",
            "type": "leaf",
            "state": {
              "type": "markdown",
              "state": {
                "file": "【文章目录】/【5 - 社会科学】/580 - 法律/582 - 中国法规/本该免费.md",
                "mode": "source",
                "source": false
              },
              "icon": "lucide-file",
              "title": "本该免费"
            }
          },
          {
            "id": "caf9dfc5ad388b0d",
            "type": "leaf",
            "state": {
              "type": "markdown",
              "state": {
                "file": "【文章目录】/【1 - 哲学类】/190 - 伦理学/194 - 性伦理 & 亲密关系/亲密关系/论恋爱/原则/大小事.md",
                "mode": "source",
                "source": false
              },
              "icon": "lucide-file",
              "title": "大小事"
            }
          }
        ],
        "currentTab": 3
      }
    ],
    "direction": "vertical"
  },
  "left": {
    "id": "36883a0dd890aadc",
    "type": "split",
    "children": [
      {
        "id": "27a88da1b223d6ee",
        "type": "tabs",
        "children": [
          {
            "id": "7569597966c86526",
            "type": "leaf",
            "state": {
              "type": "search",
              "state": {
                "query": "她却舍不得跟你讲道理，",
                "matchingCase": true,
                "explainSearch": true,
                "collapseAll": true,
                "extraContext": false,
                "sortOrder": "byCreatedTimeReverse"
              },
              "icon": "lucide-search",
              "title": "搜索"
            }
          },
          {
            "id": "366372991e7a9040",
            "type": "leaf",
            "state": {
              "type": "bookmarks",
              "state": {},
              "icon": "lucide-bookmark",
              "title": "书签"
            }
          },
          {
            "id": "4879eced09a10136",
            "type": "leaf",
            "state": {
              "type": "file-explorer",
              "state": {
                "sortOrder": "byModifiedTime"
              },
              "icon": "lucide-folder-closed",
              "title": "文件列表"
            }
          }
        ]
      }
    ],
    "direction": "horizontal",
    "width": 348.5,
    "collapsed": true
  },
  "right": {
    "id": "667d5636990656b4",
    "type": "split",
    "children": [
      {
        "id": "10b03dbeeae1a19d",
        "type": "tabs",
        "children": [
          {
            "id": "844e37cd2e641078",
            "type": "leaf",
            "state": {
              "type": "backlink",
              "state": {
                "file": "【文章目录】/【1 - 哲学类】/190 - 伦理学/194 - 性伦理 & 亲密关系/亲密关系/论恋爱/原则/大小事.md",
                "collapseAll": true,
                "extraContext": false,
                "sortOrder": "alphabetical",
                "showSearch": false,
                "searchQuery": "",
                "backlinkCollapsed": false,
                "unlinkedCollapsed": true
              },
              "icon": "links-coming-in",
              "title": "大小事 的反向链接列表"
            }
          },
          {
            "id": "727ef7e1831ef234",
            "type": "leaf",
            "state": {
              "type": "tag",
              "state": {
                "sortOrder": "alphabetical",
                "useHierarchy": true
              },
              "icon": "lucide-tags",
              "title": "标签"
            }
          },
          {
            "id": "bf225de6acac63ea",
            "type": "leaf",
            "state": {
              "type": "all-properties",
              "state": {
                "sortOrder": "frequency",
                "showSearch": false,
                "searchQuery": ""
              },
              "icon": "lucide-archive",
              "title": "添加笔记属性"
            }
          }
        ],
        "currentTab": 1
      }
    ],
    "direction": "horizontal",
    "width": 200
  },
  "left-ribbon": {
    "hiddenItems": {
      "switcher:打开快速切换": false,
      "graph:查看关系图谱": false,
      "canvas:新建白板": false,
      "command-palette:打开命令面板": false,
      "markdown-importer:打开 Markdown 格式转换器": false
    }
  },
  "active": "06b546f6b6740145",
  "lastOpenFiles": [
    "【文章目录】/【1 - 哲学类】/190 - 伦理学/194 - 性伦理 & 亲密关系/亲密关系/论恋爱/原则/大小事.md",
    "【文章目录】/【9 - 艺术类】/900 - 艺术总论/哲学的艺术.md",
    "【文章目录】/【5 - 社会科学】/580 - 法律/582 - 中国法规/本该免费.md",
    "【文章目录】/【1 - 哲学类】/170 - 心理学/173 - 一般心理/情绪/失望.md",
    "【文章目录】/【1 - 哲学类】/190 - 伦理学/198 - 职业伦理/选择与规划/程序员前景.md",
    "【文章目录】/【1 - 哲学类】/190 - 伦理学/192 - 个人伦理/自强/谁的责任.md",
    "【文章目录】/【1 - 哲学类】/190 - 伦理学/194 - 性伦理 & 亲密关系/亲密关系/论恋爱/原理/贪爱相生.md",
    "【文章目录】/【1 - 哲学类】/160 - 形而上学/160 - 形而上学总论/论功夫/学好语文.md",
    "【文章目录】/【8 - 语言文学类】/810 - 文学总论/辞源.md",
    "【文章目录】/【1 - 哲学类】/190 - 伦理学/192 - 个人伦理/修养/被讨厌.md",
    "【文章目录】/【1 - 哲学类】/160 - 形而上学/162 - 方法论/论处世/交友之道/朋友与学习.md",
    "【文章目录】/【1 - 哲学类】/150 - 逻辑学/153 - 科学方法论/3. 案例分析/极端的实践标准.md",
    "【文章目录】/【1 - 哲学类】/190 - 伦理学/194 - 性伦理 & 亲密关系/亲密关系/论恋爱/原理/恋爱原理.md",
    "【文章目录】/【1 - 哲学类】/190 - 伦理学/194 - 性伦理 & 亲密关系/亲密关系/论恋爱/禁忌/所托非人.md",
    "【文章目录】/【1 - 哲学类】/190 - 伦理学/192 - 个人伦理/修养/静气.md",
    "沙海拾金/核心能力/核心能力 - 房屋布局表述1.md",
    "待归档/鼠标垫.md",
    "待归档/预期不良.md",
    "待归档/金牛痘.md",
    "待归档/重礼.md",
    "待归档/追悔若及.md",
    "待归档/走出帐篷.md",
    "待归档/财路通天.md",
    "待归档/贞子.md",
    "待归档/谢罪.md",
    "待归档/诤谏.md",
    "debug.log",
    "md/Nell",
    "md/N",
    "md",
    "【文章目录】/【2 - 信仰类】/神学评论区",
    "爱发电/南斗集",
    "爱发电",
    "爱发电/会员专享",
    "爱发电/钩沉",
    "沙海拾金/想法待整理",
    "转载授权/1-鼓励利用我的内容盈利.jpeg",
    "转载授权/2-授权条款更新.png",
    "_附件/Screenshot 2022-12-02 at 11.01.55.png",
    "_附件/Screen Shot 2022-06-10 at 19.46.07.png",
    "_附件/Screen Shot 2022-06-10 at 19.46.01.png",
    "Untitled.canvas",
    "待移除/_附件/Screen Shot 2022-06-10 at 19.46.07.png",
    "待移除/_附件/Screenshot 2022-12-02 at 11.01.55.png",
    "待移除/_附件/Screenshot 2022-12-31 at 07.25.12.png",
    "待移除/_附件/Screenshot 2022-12-31 at 07.25.21.png",
    "待移除/_附件/Screenshot 2022-12-31 at 07.25.27.png"
  ]
}